triton_helpers.cpython-39-x86_64-linux-gnu.so
triton.cpython-39-x86_64-linux-gnu.so
nexfort_codegen_extension.cpython-39-x86_64-linux-gnu.so
nexfort-0.1.dev330.dist-info/LICENSE
nexfort-0.1.dev330.dist-info/top_level.txt
nexfort-0.1.dev330.dist-info/METADATA
nexfort-0.1.dev330.dist-info/WHEEL
nexfort-0.1.dev330.dist-info/RECORD
nexfort/_version.py
nexfort/__main__.py
nexfort/_C.cpython-39-x86_64-linux-gnu.so
nexfort/check_compiled_env_meta.py
nexfort/common.cpython-39-x86_64-linux-gnu.so
nexfort/_C_inductor.cpython-39-x86_64-linux-gnu.so
nexfort/__init__.py
nexfort/_C_cuda.cpython-39-x86_64-linux-gnu.so
nexfort/fx_compiler/pre_trace.cpython-39-x86_64-linux-gnu.so
nexfort/fx_compiler/__init__.cpython-39-x86_64-linux-gnu.so
nexfort/fx_compiler/utils.cpython-39-x86_64-linux-gnu.so
nexfort/fx_compiler/mode.cpython-39-x86_64-linux-gnu.so
nexfort/fx_compiler/fx_compiler.cpython-39-x86_64-linux-gnu.so
nexfort/fx_compiler/overrides.cpython-39-x86_64-linux-gnu.so
nexfort/fx_compiler/decomps.cpython-39-x86_64-linux-gnu.so
nexfort/fx_compiler/pre_trace_fx_passes.cpython-39-x86_64-linux-gnu.so
nexfort/fx_compiler/config.py
nexfort/fx_compiler/compile_cache/__init__.cpython-39-x86_64-linux-gnu.so
nexfort/fx_compiler/compile_cache/utils.cpython-39-x86_64-linux-gnu.so
nexfort/fx_compiler/compile_cache/compiled_graph_convert.cpython-39-x86_64-linux-gnu.so
nexfort/fx_compiler/compile_cache/compiled_graph_cache.cpython-39-x86_64-linux-gnu.so
nexfort/fx_compiler/compile_cache/compiled_graph_entry.cpython-39-x86_64-linux-gnu.so
nexfort/fx_compiler/compile_cache/_runtime_wrappers.cpython-39-x86_64-linux-gnu.so
nexfort/dynamo/__init__.cpython-39-x86_64-linux-gnu.so
nexfort/dynamo/backends/__init__.cpython-39-x86_64-linux-gnu.so
nexfort/dynamo/backends/nexfort.cpython-39-x86_64-linux-gnu.so
nexfort/dynamo/backends/registry.cpython-39-x86_64-linux-gnu.so
nexfort/ao/__init__.cpython-39-x86_64-linux-gnu.so
nexfort/profilers/pretty_profile.py
nexfort/profilers/__init__.py
nexfort/profilers/auto_profiler.py
nexfort/profilers/cprofile.py
nexfort/cuda/graphs.cpython-39-x86_64-linux-gnu.so
nexfort/cuda/__init__.cpython-39-x86_64-linux-gnu.so
