Metadata-Version: 2.1
Name: nexfort
Version: 0.1.dev330
Summary: Next Generation Extension for PyTorch
Author: SiliconFlow
Project-URL: Repository, https://github.com/siliconflow/nexfort
Requires-Python: >=3.8
License-File: LICENSE
Requires-Dist: packaging
Requires-Dist: torch <=2.5.1,>=2.3.0
Requires-Dist: loguru
Requires-Dist: httpx
Requires-Dist: cryptography
Requires-Dist: pycryptodome
Requires-Dist: tenacity
Provides-Extra: all
Provides-Extra: dev
Requires-Dist: pre-commit ; extra == 'dev'
Requires-Dist: pytest ; extra == 'dev'
Requires-Dist: tabulate ; extra == 'dev'
Requires-Dist: matplotlib ; extra == 'dev'
Requires-Dist: pandas ; extra == 'dev'
